policystream.py
c7n_policystream-0.4.48.dist-info/METADATA
c7n_policystream-0.4.48.dist-info/WHEEL
c7n_policystream-0.4.48.dist-info/entry_points.txt
c7n_policystream-0.4.48.dist-info/RECORD
