Metadata-Version: 2.4
Name: c7n_policystream
Version: 0.4.48
Summary: Cloud Custodian - Git Commits as Logical Policy Changes
Project-URL: homepage, https://cloudcustodian.io
Project-URL: repository, https://github.com/cloud-custodian/cloud-custodian
Project-URL: documentation, https://cloudcustodian.io/docs/
Author: Cloud Custodian Project
License-Expression: Apache-2.0
Classifier: License :: OSI Approved :: Apache Software License
Classifier: Topic :: System :: Distributed Computing
Classifier: Topic :: System :: Systems Administration
Requires-Python: <4.0.0,>=3.9.2
Requires-Dist: boto3 ==1.42.27
Requires-Dist: c7n ==0.9.49
Requires-Dist: click ==8.3.1
Requires-Dist: pygit2 ==1.19.1
Requires-Dist: pyyaml ==6.0.3
Requires-Dist: requests ==2.32.5
